{
  "celestitalBodies": [
    {
      "name": "Mercury",
      "semiMajorAxis": 0.38709927,
      "eccentricity": 0.20563593,
      "meanLongitude": 252.2503235,
      "longitudeOfPerihelion": 77.45779628,
      "longitudeOfAscendingNode": 48.33076593,
      "size": 10,
      "color": "#8C7853"
    },
    {
      "name": "Venus",
      "semiMajorAxis": 0.72333566,
      "eccentricity": 0.00677672,
      "meanLongitude": 181.9790995,
      "longitudeOfPerihelion": 131.60246718,
      "longitudeOfAscendingNode": 76.67984255,
      "size": 10,
      "color": "#FFC649"
    },
    {
      "name": "Terra",
      "semiMajorAxis": 1.00000261,
      "eccentricity": 0.01671123,
      "meanLongitude": 100.46457166,
      "longitudeOfPerihelion": 102.93768193,
      "longitudeOfAscendingNode": 0.0,
      "size": 10,
      "color": "#4A90E2"
    },
    {
      "name": "Mars",
      "semiMajorAxis": 1.52371034,
      "eccentricity": 0.0933941,
      "meanLongitude": -4.55343205,
      "longitudeOfPerihelion": -23.94362959,
      "longitudeOfAscendingNode": 49.55953891,
      "size": 10,
      "color": "#CD5C5C"
    },
    {
      "name": "Jupiter",
      "semiMajorAxis": 5.202887,
      "eccentricity": 0.04838624,
      "meanLongitude": 34.39644051,
      "longitudeOfPerihelion": 14.72847983,
      "longitudeOfAscendingNode": 100.47390909,
      "size": 10,
      "color": "#C88B3A"
    },
    {
      "name": "Saturn",
      "semiMajorAxis": 9.53667594,
      "eccentricity": 0.05386179,
      "meanLongitude": 49.95424423,
      "longitudeOfPerihelion": 92.59887831,
      "longitudeOfAscendingNode": 113.66242448,
      "size": 10,
      "color": "#FAD5A5"
    },
    {
      "name": "Uranus",
      "semiMajorAxis": 19.18916464,
      "eccentricity": 0.04725744,
      "meanLongitude": 313.23810451,
      "longitudeOfPerihelion": 170.9542763,
      "longitudeOfAscendingNode": 74.01692503,
      "size": 10,
      "color": "#4FD0E7"
    },
    {
      "name": "Neptune",
      "semiMajorAxis": 30.06992276,
      "eccentricity": 0.00859048,
      "meanLongitude": -55.12002969,
      "longitudeOfPerihelion": 44.96476227,
      "longitudeOfAscendingNode": 131.78422574,
      "size": 10,
      "color": "#4166F5"
    }
  ]
}
